funbuild/__init__.py
funbuild/core/__init__.py
funbuild/core/core.py
funbuild/core/version.py
funbuild/git/__init__.py
funbuild/git/repo.py
funbuild/manage/__init__.py
funbuild/manage/core.py
funbuild/manage/port.md
funbuild/manage/supervisord.conf
funbuild/shell/__init__.py
funbuild/shell/core.py
funbuild/temp/__init__.py
funbuild/temp/core.json
funbuild/temp/core.py
funbuild/tool/__init__.py
funbuild/tool/build.py
funbuild/tool/fastapi.py
funbuild-202308241954.dist-info/LICENSE
funbuild-202308241954.dist-info/METADATA
funbuild-202308241954.dist-info/WHEEL
funbuild-202308241954.dist-info/entry_points.txt
funbuild-202308241954.dist-info/top_level.txt
funbuild-202308241954.dist-info/RECORD
