Metadata-Version: 2.1
Name: funbuild
Version: 202308241954
Summary: funbuild
Home-page: https://github.com/1007530194
Author: bingtao
Author-email: 1007530194@qq.com
License-File: LICENSE
Requires-Dist: GitPython
